<?xml version="1.0" encoding="UTF-8"?>
<sprites xmlns:xsi="http://www.w3.org/2001/XMLSchema-instance" xmlns="pmdmmo"
  xsi:schemaLocation="pmdmmo ../data/xsd/spritesets.xsd">
  <pokemon id="0" size="32">
    <attack duration="32">4</attack>
    <hurt duration="32">1</hurt>
    <idle duration="32">2</idle>
    <move duration="32">3</move>
    <sleep duration="32">0</sleep>
    <spe1 duration="32">4</spe1>
  </pokemon>
  <pokemon id="1" size="32">
    <attack duration="20,6,6">4,5,3</attack>
    <idle duration="70,6,6">3,4,5</idle>
    <move duration="10,10,10">4,5,3</move>
    <spe1 duration="20,40">6,7</spe1>
    <spe2 duration="20,40">8,9</spe2>
    <victory duration="10,40">6,7</victory>
    <wake duration="2,2,2,2,2,2">0,1,0,1,0,1</wake>
  </pokemon>
  <pokemon id="4" size="32">
    <attack duration="20,6,6">6,7,8</attack>
    <attack2 duration="20,6,6,6">6,3,9,10</attack2>
    <idle duration="70,6,6">3,4,5</idle>
    <move duration="10,10,10,10">3,4,3,5</move>
    <spe1 duration="60">11</spe1>
  </pokemon>
  <pokemon id="7" size="32" y="20">
    <attack duration="10,10,10">3,4,5</attack>
    <idle duration="70,6,6">3,4,5</idle>
    <move duration="10,10,10">3,4,5</move>
    <spe1 duration="20,5,5,5,5">6,7,8,7,8</spe1>
    <spe2 duration="60">9</spe2>
  </pokemon>
  <pokemon id="16" size="32">
    <attack duration="2,2,2,2,2,2,2,2,20">6,7,6,7,6,7,6,7,8</attack>
    <idle duration="60,10">3,4</idle>
    <move duration="15,15,15">3,5,4</move>
    <spe1 duration="2,2,2,2,2,2,2,2">6,7,6,7,6,7,6,7</spe1>
  </pokemon>
  <pokemon id="19" size="32">
    <attack duration="5,5,5,20">3,4,5,6</attack>
    <idle duration="30,5,5,5">3,4,3,4</idle>
    <move duration="15,15,15">3,4,5</move>
    <spe1 duration="5,10,8">3,4,7</spe1>
  </pokemon>
  <pokemon id="25" size="32">
    <attack duration="5,15,5">3,4,3</attack>
    <idle duration="30,15">3,4</idle>
    <move duration="10,10,10,10">3,5,3,6</move>
    <spe1 duration="10,15">7,8</spe1>
  </pokemon>
  <pokemon id="52" size="32">
    <attack duration="5,10,5">6,7,8</attack>
    <idle duration="30,5,5,5">3,4,3,5</idle>
    <move duration="10,10,10,10">3,4,3,5</move>
    <spe1 duration="30">9</spe1>
  </pokemon>
  <pokemon id="66" size="32">
    <attack duration="10,5,5,10">6,7,8,9</attack>
    <attack2 duration="10,5,15">4,10,11</attack2>
    <idle duration="40,10">3,4</idle>
    <move duration="10,10,10,10">3,4,3,5</move>
    <spe1 duration="40">12</spe1>
  </pokemon>
  <pokemon id="69" size="32">
    <attack duration="10,10,10">7,8,9</attack>
    <idle duration="40,40">3,4</idle>
    <move duration="10,10,10">3,5,6</move>
    <spe1 duration="10,10,10">6,10,11</spe1>
  </pokemon>
  <pokemon id="102" size="32">
    <attack duration="5,5,5,20">3,5,4,6</attack>
    <idle duration="40,20">3,4</idle>
    <move duration="10,10,10">5,3,4</move>
    <spe1 duration="10,10,20">3,5,7</spe1>
  </pokemon>
  <pokemon id="104" size="32">
    <attack duration="20,5,10">6,7,8</attack>
    <idle duration="40,10">3,4</idle>
    <move duration="10,10,10,10">3,4,3,5</move>
    <spe1 duration="30">8</spe1>
  </pokemon>
  <pokemon id="133" size="32">
    <attack duration="10,10,10">6,7,5</attack>
    <idle duration="30,30">3,4</idle>
    <move duration="15,15,15">5,6,7</move>
    <spe1 duration="10,10,10,10">8,9,8,9</spe1>
  </pokemon>
  <pokemon id="152" size="32">
    <attack duration="10,10,10,10">3,5,3,6</attack>
    <idle duration="40,5,15">3,4,5</idle>
    <move duration="10,10,10,10">3,5,3,6</move>
    <spe1 duration="40,20">4,7</spe1>
  </pokemon>
  <pokemon id="155" size="32">
    <attack duration="20,20,20">7,8,9</attack>
    <idle duration="35,25">3,4</idle>
    <move duration="10,10,10,10">3,5,3,6</move>
    <spe1 duration="15,15,15,15">6,9,10,4</spe1>
  </pokemon>
  <pokemon id="158" size="32">
    <attack duration="10,2,2,5,5">8,9,10,11,12</attack>
    <idle duration="40,10,10">3,4,5</idle>
    <move duration="10,10,10,10">3,6,3,7</move>
    <spe1 duration="25,25,10">4,5,3</spe1>
  </pokemon>
  <pokemon id="191" size="32">
    <attack duration="10,30">4,5</attack>
    <idle duration="20,15">3,4</idle>
    <move duration="20,15">3,4</move>
    <spe1 duration="50">6</spe1>
  </pokemon>
  <pokemon id="252" size="32">
    <attack duration="15,15,15">5,4,6</attack>
    <idle duration="60">3</idle>
    <move duration="10,10,10,10">4,5,4,6</move>
    <spe1 duration="50">7</spe1>
  </pokemon>
  <pokemon id="255" size="32">
    <attack duration="15,15,15">6,3,7</attack>
    <idle duration="40,10,10">3,4,5</idle>
    <move duration="10,10,10,10">3,6,3,7</move>
    <spe1 duration="5,5,20">5,6,8</spe1>
  </pokemon>
  <pokemon id="258" size="32">
    <attack duration="15,15,15">3,4,5</attack>
    <idle duration="60,10,10">3,4,5</idle>
    <move duration="15,15,15">3,4,5</move>
    <spe1 duration="50">6</spe1>
  </pokemon>
  <pokemon id="260" size="48" bigshadow="true">
    <attack duration="15,20">7,5</attack>
    <idle duration="60,20">3,4</idle>
    <move duration="15,10,15,10">5,3,6,3</move>
    <spe1 duration="50">7</spe1>
  </pokemon>
  <pokemon id="261" size="32">
    <attack duration="10,10,10">8,9,10</attack>
    <idle duration="30,6,6,6,6,6">3,4,5,4,5,4</idle>
    <move duration="10,10,10">6,7,8</move>
    <spe1 duration="10,40">4,10</spe1>
  </pokemon>
  <pokemon id="265" size="32">
    <attack duration="30,5,10">3,5,6</attack>
    <idle duration="30,30">3,4</idle>
    <move duration="20,15,15">3,5,6</move>
    <spe1 duration="10,40">3,4</spe1>
  </pokemon>
  <pokemon id="300" size="48">
    <attack duration="10,5,10">3,5,6</attack>
    <idle duration="20,10,10,10">3,4,3,4</idle>
    <move duration="15,15,15">5,6,3</move>
    <spe1 duration="10,10,10,10,10">6,7,8,7,8</spe1>
  </pokemon>
  <pokemon id="311" size="32">
    <attack duration="10,10,10">3,4,6</attack>
    <idle duration="30,5,5,5">3,5,3,5</idle>
    <move duration="20,20,20,20">3,4,3,5</move>
    <spe1 duration="40,10">6,7</spe1>
  </pokemon>
  <pokemon id="312" size="32">
    <attack duration="10,10,10">3,5,6</attack>
    <idle duration="30,5,5,5">3,4,3,4</idle>
    <move duration="20,20,20,20">3,5,3,4</move>
    <spe1 duration="40,10">6,7</spe1>
  </pokemon>
  <pokemon id="343" size="32">
    <attack duration="40">4</attack>
    <hurt duration="32">3</hurt>
    <idle duration="70">4</idle>
    <move duration="40">4</move>
    <sleep duration="20,15,15">1,2,0</sleep>
    <spe1 duration="40">5</spe1>
  </pokemon>
</sprites>
